UART/rx_uart.v
module rx_uart
#(parameter CLKS_PER_BIT = 217)
(
    input clk,
    input rx_serial,
    output rx_dv,
    output rx_active,
    output [7:0] out_data
);
    
    parameter IDLE         = 3'b000;
    parameter RX_START_BIT = 3'b001;
    parameter RX_DATA_BITS = 3'b010;
    parameter RX_STOP_BIT  = 3'b011;
 
    reg [2:0] RX_STATE = 0;
    reg [7:0] clk_counter = 0;
    reg [2:0] rx_bit_index = 0;
    reg [7:0] RX_DATA = 0;
    reg rx_active = 0;

    always @(posedge clk) begin
        
        case (RX_STATE)
            IDLE : 
                begin
                    clk_counter <= 0;
                    rx_bit_index <= 0;

                    if (rx_serial == 1'b0) begin
                        // Start bit detected
                        rx_active <= 1'b1;
                        RX_STATE <= RX_START_BIT;
                    end
                    else begin
                        RX_STATE <= IDLE;
                    end
                end

            RX_START_BIT : 
                begin
                    if (clk_counter == (CLKS_PER_BIT-1)/2)begin
                        if (rx_serial == 1'b0) begin
                            clk_counter <= 0;
                            RX_STATE <= RX_DATA_BITS;
                        end
                        else begin
                            RX_STATE <= IDLE;
                        end
                    end
                    else begin
                        clk_counter <= clk_counter + 1;
                        RX_STATE <= RX_START_BIT;
                    end

                    // if (clk_counter < CLKS_PER_BIT-1) begin
                    //     // Check middle of start bit to make sure it's still low
                    //     if (clk_counter == (CLKS_PER_BIT)/2)begin
                    //         if (rx_serial != 1'b0) begin
                    //             clk_counter <= 0;
                    //             RX_STATE <= IDLE;
                    //         end
                    //     end
                    //     clk_counter <= clk_counter + 1;
                    //     RX_STATE <= RX_START_BIT;
                    // end
                    // else begin
                    //     clk_counter <= 0;
                    //     RX_STATE <= RX_DATA_BITS;
                    // end
                end

            RX_DATA_BITS :
                begin
                    if (clk_counter < CLKS_PER_BIT-1) begin
                        // if (clk_counter == (CLKS_PER_BIT)/2)begin
                        //     if (rx_serial != 1'b0) begin
                        //         clk_counter <= 0;
                        //         RX_STATE <= IDLE;
                        //     end
                        // end
                        clk_counter <= clk_counter + 1;
                        RX_STATE <= RX_DATA_BITS;
                    end
                    else begin
                        clk_counter <= 0;
                        RX_DATA[rx_bit_index] <= rx_serial;

                        if(rx_bit_index < 7) begin
                            rx_bit_index <= rx_bit_index + 1;
                            RX_STATE <= RX_DATA_BITS;
                        end
                        else begin
                            rx_bit_index <= 0;
                            RX_STATE <= RX_STOP_BIT;
                        end
                    end
                end

            RX_STOP_BIT :
                begin
                    if (clk_counter < CLKS_PER_BIT-1) begin
                        clk_counter <= clk_counter + 1;
                        RX_STATE <= RX_STOP_BIT;
                    end
                    else begin
                        rx_active <= 0;
                        clk_counter <= 0;
                        RX_STATE <= IDLE;
                    end
                end

            default: 
                RX_STATE <= IDLE;
                
        endcase
    end

    assign out_data = RX_DATA;
    
endmodule

UART/tx_uart.v
module tx_uart
#(parameter CLKS_PER_BIT = 217)
 (
    input clk,
    input [7:0] in_data,
    input tx_dv,
    output tx_active,
    output reg tx_serial
);
    
    parameter IDLE         = 3'b000;
    parameter TX_START_BIT = 3'b001;
    parameter TX_DATA_BITS = 3'b010;
    parameter TX_STOP_BIT  = 3'b011;
    
    reg [2:0] TX_STATE = 0;
    reg [7:0] clk_counter = 0;
    reg [2:0] bit_index = 0;
    reg [7:0] TX_DATA = 0;
    reg tx_active = 0;

    always @(posedge clk) begin

        case (TX_STATE)
           IDLE :
                begin
                    tx_serial <= 1'b1;
                    clk_counter <= 1'b0;
                    bit_index <= 1'b0;

                    if (tx_dv == 1'b1)begin
                        tx_active <= 1'b1;
                        TX_DATA <= in_data;
                        TX_STATE <= TX_START_BIT;
                    end
                    else begin
                        TX_STATE <= IDLE;
                    end
                end 

            TX_START_BIT :
                begin
                    tx_serial <= 1'b0;

                    if (clk_counter < CLKS_PER_BIT-1) begin
                        clk_counter <= clk_counter + 1;
                        TX_STATE <= TX_START_BIT;
                    end
                    else begin
                        clk_counter <= 0;
                        TX_STATE <= TX_DATA_BITS;
                    end
                end

            TX_DATA_BITS :
                begin
                    tx_serial <= TX_DATA[bit_index];

                    if (clk_counter < CLKS_PER_BIT-1) begin
                        clk_counter <= clk_counter + 1;
                        TX_STATE <= TX_DATA_BITS; 
                    end
                    else begin
                        clk_counter <= 0;

                        if (bit_index < 7) begin
                            bit_index <= bit_index + 1;
                            TX_STATE <= TX_DATA_BITS;
                        end
                        else begin
                            bit_index <= 0;
                            TX_STATE <= TX_STOP_BIT;
                        end
                    end
                end

            TX_STOP_BIT :
                begin
                    tx_serial <= 1'b1;

                    if(clk_counter < CLKS_PER_BIT-1) begin
                        clk_counter <= clk_counter + 1;
                        TX_STATE <= TX_STOP_BIT;
                    end
                    else begin
                        tx_active <= 1'b0;
                        clk_counter <= 0;
                        TX_STATE <= IDLE;
                    end
                end


            default: 
                TX_STATE <= IDLE;

        endcase
        
    end
    // `ifdef COCOTB_SIM
    //     initial begin
    //         $dumpfile("tx_uart.vcd");
    //         $dumpvars(0,tx_uart);
    //         #1;
    //     end
    // `endif


endmodule

UART/UART_COM.sv
`timescale 1ns/1ps

`include "tx_uart.v"
`include "rx_uart.v"

module UART_COM ();

    parameter CLKS_PER_BIT = 217;
    reg i_clock;
    reg r_tx_dv;
    reg [7:0] r_TX_Byte ;
    wire [7:0] w_RX_Byte;
    wire w_tx_serial;
    reg w_tx_active, w_rx_active;
    wire w_UART_Line;

    assign w_UART_Line = w_tx_active ? w_tx_serial : 1'b1;
    
    tx_uart #(.CLKS_PER_BIT(CLKS_PER_BIT)) tx_uart_Inst
    (
        .clk(i_clock),
        .tx_dv(r_tx_dv),
        .in_data(r_TX_Byte),
        .tx_active(w_tx_active),
        .tx_serial(w_tx_serial)
    );

    rx_uart #(.CLKS_PER_BIT(CLKS_PER_BIT)) rx_uart_Inst
    (
        .clk(i_clock),
        .out_data(w_RX_Byte),
        .rx_active(w_rx_active),
        .rx_serial(w_UART_Line)
    );
    
    
    `ifdef COCOTB_SIM
        initial begin
            $dumpfile("UART_COMM.vcd");
            $dumpvars(0);
            #1;
        end
    `endif

endmodule

UART/UART_COMM.vcd
$date
	Tue Oct 12 01:09:35 2021
$end
$version
	Icarus Verilog
$end
$timescale
	1ps
$end
$scope module UART_COM $end
$var wire 1 ! w_tx_serial $end
$var wire 1 " w_tx_active $end
$var wire 1 # w_rx_active $end
$var wire 1 $ w_UART_Line $end
$var wire 8 % w_RX_Byte [7:0] $end
$var reg 1 & i_clock $end
$var reg 8 ' r_TX_Byte [7:0] $end
$var reg 1 ( r_tx_dv $end
$scope module rx_uart_Inst $end
$var wire 1 & clk $end
$var wire 8 ) out_data [7:0] $end
$var wire 1 * rx_dv $end
$var wire 1 $ rx_serial $end
$var reg 8 + RX_DATA [7:0] $end
$var reg 3 , RX_STATE [2:0] $end
$var reg 8 - clk_counter [7:0] $end
$var reg 1 # rx_active $end
$var reg 3 . rx_bit_index [2:0] $end
$upscope $end
$scope module tx_uart_Inst $end
$var wire 1 & clk $end
$var wire 8 / in_data [7:0] $end
$var wire 1 ( tx_dv $end
$var reg 8 0 TX_DATA [7:0] $end
$var reg 3 1 TX_STATE [2:0] $end
$var reg 3 2 bit_index [2:0] $end
$var reg 8 3 clk_counter [7:0] $end
$var reg 1 " tx_active $end
$var reg 1 ! tx_serial $end
$upscope $end
$upscope $end
$enddefinitions $end
#0
$dumpvars
b0 3
b0 2
b0 1
b0 0
bx /
b0 .
b0 -
b0 ,
b0 +
z*
b0 )
0(
bx '
1&
b0 %
1$
0#
0"
1!
$end
#5000000
0&
#10000000
1(
b11000001 '
b11000001 /
1&
#15000000
0&
#20000000
0(
b1 1
b11000001 0
1"
1&
#25000000
0&
#30000000
0$
b1 3
0!
1&
#35000000
0&
#40000000
b10 3
b1 ,
1#
1&
#45000000
0&
#50000000
b1 -
b11 3
1&
#55000000
0&
#60000000
b100 3
b10 -
1&
#65000000
0&
#70000000
b11 -
b101 3
1&
#75000000
0&
#80000000
b110 3
b100 -
1&
#85000000
0&
#90000000
b101 -
b111 3
1&
#95000000
0&
#100000000
b1000 3
b110 -
1&
#105000000
0&
#110000000
b111 -
b1001 3
1&
#115000000
0&
#120000000
b1010 3
b1000 -
1&
#125000000
0&
#130000000
b1001 -
b1011 3
1&
#135000000
0&
#140000000
b1100 3
b1010 -
1&
#145000000
0&
#150000000
b1011 -
b1101 3
1&
#155000000
0&
#160000000
b1110 3
b1100 -
1&
#165000000
0&
#170000000
b1101 -
b1111 3
1&
#175000000
0&
#180000000
b10000 3
b1110 -
1&
#185000000
0&
#190000000
b1111 -
b10001 3
1&
#195000000
0&
#200000000
b10010 3
b10000 -
1&
#205000000
0&
#210000000
b10001 -
b10011 3
1&
#215000000
0&
#220000000
b10100 3
b10010 -
1&
#225000000
0&
#230000000
b10011 -
b10101 3
1&
#235000000
0&
#240000000
b10110 3
b10100 -
1&
#245000000
0&
#250000000
b10101 -
b10111 3
1&
#255000000
0&
#260000000
b11000 3
b10110 -
1&
#265000000
0&
#270000000
b10111 -
b11001 3
1&
#275000000
0&
#280000000
b11010 3
b11000 -
1&
#285000000
0&
#290000000
b11001 -
b11011 3
1&
#295000000
0&
#300000000
b11100 3
b11010 -
1&
#305000000
0&
#310000000
b11011 -
b11101 3
1&
#315000000
0&
#320000000
b11110 3
b11100 -
1&
#325000000
0&
#330000000
b11101 -
b11111 3
1&
#335000000
0&
#340000000
b100000 3
b11110 -
1&
#345000000
0&
#350000000
b11111 -
b100001 3
1&
#355000000
0&
#360000000
b100010 3
b100000 -
1&
#365000000
0&
#370000000
b100001 -
b100011 3
1&
#375000000
0&
#380000000
b100100 3
b100010 -
1&
#385000000
0&
#390000000
b100011 -
b100101 3
1&
#395000000
0&
#400000000
b100110 3
b100100 -
1&
#405000000
0&
#410000000
b100101 -
b100111 3
1&
#415000000
0&
#420000000
b101000 3
b100110 -
1&
#425000000
0&
#430000000
b100111 -
b101001 3
1&
#435000000
0&
#440000000
b101010 3
b101000 -
1&
#445000000
0&
#450000000
b101001 -
b101011 3
1&
#455000000
0&
#460000000
b101100 3
b101010 -
1&
#465000000
0&
#470000000
b101011 -
b101101 3
1&
#475000000
0&
#480000000
b101110 3
b101100 -
1&
#485000000
0&
#490000000
b101101 -
b101111 3
1&
#495000000
0&
#500000000
b110000 3
b101110 -
1&
#505000000
0&
#510000000
b101111 -
b110001 3
1&
#515000000
0&
#520000000
b110010 3
b110000 -
1&
#525000000
0&
#530000000
b110001 -
b110011 3
1&
#535000000
0&
#540000000
b110100 3
b110010 -
1&
#545000000
0&
#550000000
b110011 -
b110101 3
1&
#555000000
0&
#560000000
b110110 3
b110100 -
1&
#565000000
0&
#570000000
b110101 -
b110111 3
1&
#575000000
0&
#580000000
b111000 3
b110110 -
1&
#585000000
0&
#590000000
b110111 -
b111001 3
1&
#595000000
0&
#600000000
b111010 3
b111000 -
1&
#605000000
0&
#610000000
b111001 -
b111011 3
1&
#615000000
0&
#620000000
b111100 3
b111010 -
1&
#625000000
0&
#630000000
b111011 -
b111101 3
1&
#635000000
0&
#640000000
b111110 3
b111100 -
1&
#645000000
0&
#650000000
b111101 -
b111111 3
1&
#655000000
0&
#660000000
b1000000 3
b111110 -
1&
#665000000
0&
#670000000
b111111 -
b1000001 3
1&
#675000000
0&
#680000000
b1000010 3
b1000000 -
1&
#685000000
0&
#690000000
b1000001 -
b1000011 3
1&
#695000000
0&
#700000000
b1000100 3
b1000010 -
1&
#705000000
0&
#710000000
b1000011 -
b1000101 3
1&
#715000000
0&
#720000000
b1000110 3
b1000100 -
1&
#725000000
0&
#730000000
b1000101 -
b1000111 3
1&
#735000000
0&
#740000000
b1001000 3
b1000110 -
1&
#745000000
0&
#750000000
b1000111 -
b1001001 3
1&
#755000000
0&
#760000000
b1001010 3
b1001000 -
1&
#765000000
0&
#770000000
b1001001 -
b1001011 3
1&
#775000000
0&
#780000000
b1001100 3
b1001010 -
1&
#785000000
0&
#790000000
b1001011 -
b1001101 3
1&
#795000000
0&
#800000000
b1001110 3
b1001100 -
1&
#805000000
0&
#810000000
b1001101 -
b1001111 3
1&
#815000000
0&
#820000000
b1010000 3
b1001110 -
1&
#825000000
0&
#830000000
b1001111 -
b1010001 3
1&
#835000000
0&
#840000000
b1010010 3
b1010000 -
1&
#845000000
0&
#850000000
b1010001 -
b1010011 3
1&
#855000000
0&
#860000000
b1010100 3
b1010010 -
1&
#865000000
0&
#870000000
b1010011 -
b1010101 3
1&
#875000000
0&
#880000000
b1010110 3
b1010100 -
1&
#885000000
0&
#890000000
b1010101 -
b1010111 3
1&
#895000000
0&
#900000000
b1011000 3
b1010110 -
1&
#905000000
0&
#910000000
b1010111 -
b1011001 3
1&
#915000000
0&
#920000000
b1011010 3
b1011000 -
1&
#925000000
0&
#930000000
b1011001 -
b1011011 3
1&
#935000000
0&
#940000000
b1011100 3
b1011010 -
1&
#945000000
0&
#950000000
b1011011 -
b1011101 3
1&
#955000000
0&
#960000000
b1011110 3
b1011100 -
1&
#965000000
0&
#970000000
b1011101 -
b1011111 3
1&
#975000000
0&
#980000000
b1100000 3
b1011110 -
1&
#985000000
0&
#990000000
b1011111 -
b1100001 3
1&
#995000000
0&
#1000000000
b1100010 3
b1100000 -
1&
#1005000000
0&
#1010000000
b1100001 -
b1100011 3
1&
#1015000000
0&
#1020000000
b1100100 3
b1100010 -
1&
#1025000000
0&
#1030000000
b1100011 -
b1100101 3
1&
#1035000000
0&
#1040000000
b1100110 3
b1100100 -
1&
#1045000000
0&
#1050000000
b1100101 -
b1100111 3
1&
#1055000000
0&
#1060000000
b1101000 3
b1100110 -
1&
#1065000000
0&
#1070000000
b1100111 -
b1101001 3
1&
#1075000000
0&
#1080000000
b1101010 3
b1101000 -
1&
#1085000000
0&
#1090000000
b1101001 -
b1101011 3
1&
#1095000000
0&
#1100000000
b1101100 3
b1101010 -
1&
#1105000000
0&
#1110000000
b1101011 -
b1101101 3
1&
#1115000000
0&
#1120000000
b1101110 3
b1101100 -
1&
#1125000000
0&
#1130000000
b10 ,
b0 -
b1101111 3
1&
#1135000000
0&
#1140000000
b1110000 3
b1 -
1&
#1145000000
0&
#1150000000
b10 -
b1110001 3
1&
#1155000000
0&
#1160000000
b1110010 3
b11 -
1&
#1165000000
0&
#1170000000
b100 -
b1110011 3
1&
#1175000000
0&
#1180000000
b1110100 3
b101 -
1&
#1185000000
0&
#1190000000
b110 -
b1110101 3
1&
#1195000000
0&
#1200000000
b1110110 3
b111 -
1&
#1205000000
0&
#1210000000
b1000 -
b1110111 3
1&
#1215000000
0&
#1220000000
b1111000 3
b1001 -
1&
#1225000000
0&
#1230000000
b1010 -
b1111001 3
1&
#1235000000
0&
#1240000000
b1111010 3
b1011 -
1&
#1245000000
0&
#1250000000
b1100 -
b1111011 3
1&
#1255000000
0&
#1260000000
b1111100 3
b1101 -
1&
#1265000000
0&
#1270000000
b1110 -
b1111101 3
1&
#1275000000
0&
#1280000000
b1111110 3
b1111 -
1&
#1285000000
0&
#1290000000
b10000 -
b1111111 3
1&
#1295000000
0&
#1300000000
b10000000 3
b10001 -
1&
#1305000000
0&
#1310000000
b10010 -
b10000001 3
1&
#1315000000
0&
#1320000000
b10000010 3
b10011 -
1&
#1325000000
0&
#1330000000
b10100 -
b10000011 3
1&
#1335000000
0&
#1340000000
b10000100 3
b10101 -
1&
#1345000000
0&
#1350000000
b10110 -
b10000101 3
1&
#1355000000
0&
#1360000000
b10000110 3
b10111 -
1&
#1365000000
0&
#1370000000
b11000 -
b10000111 3
1&
#1375000000
0&
#1380000000
b10001000 3
b11001 -
1&
#1385000000
0&
#1390000000
b11010 -
b10001001 3
1&
#1395000000
0&
#1400000000
b10001010 3
b11011 -
1&
#1405000000
0&
#1410000000
b11100 -
b10001011 3
1&
#1415000000
0&
#1420000000
b10001100 3
b11101 -
1&
#1425000000
0&
#1430000000
b11110 -
b10001101 3
1&
#1435000000
0&
#1440000000
b10001110 3
b11111 -
1&
#1445000000
0&
#1450000000
b100000 -
b10001111 3
1&
#1455000000
0&
#1460000000
b10010000 3
b100001 -
1&
#1465000000
0&
#1470000000
b100010 -
b10010001 3
1&
#1475000000
0&
#1480000000
b10010010 3
b100011 -
1&
#1485000000
0&
#1490000000
b100100 -
b10010011 3
1&
#1495000000
0&
#1500000000
b10010100 3
b100101 -
1&
#1505000000
0&
#1510000000
b100110 -
b10010101 3
1&
#1515000000
0&
#1520000000
b10010110 3
b100111 -
1&
#1525000000
0&
#1530000000
b101000 -
b10010111 3
1&
#1535000000
0&
#1540000000
b10011000 3
b101001 -
1&
#1545000000
0&
#1550000000
b101010 -
b10011001 3
1&
#1555000000
0&
#1560000000
b10011010 3
b101011 -
1&
#1565000000
0&
#1570000000
b101100 -
b10011011 3
1&
#1575000000
0&
#1580000000
b10011100 3
b101101 -
1&
#1585000000
0&
#1590000000
b101110 -
b10011101 3
1&
#1595000000
0&
#1600000000
b10011110 3
b101111 -
1&
#1605000000
0&
#1610000000
b110000 -
b10011111 3
1&
#1615000000
0&
#1620000000
b10100000 3
b110001 -
1&
#1625000000
0&
#1630000000
b110010 -
b10100001 3
1&
#1635000000
0&
#1640000000
b10100010 3
b110011 -
1&
#1645000000
0&
#1650000000
b110100 -
b10100011 3
1&
#1655000000
0&
#1660000000
b10100100 3
b110101 -
1&
#1665000000
0&
#1670000000
b110110 -
b10100101 3
1&
#1675000000
0&
#1680000000
b10100110 3
b110111 -
1&
#1685000000
0&
#1690000000
b111000 -
b10100111 3
1&
#1695000000
0&
#1700000000
b10101000 3
b111001 -
1&
#1705000000
0&
#1710000000
b111010 -
b10101001 3
1&
#1715000000
0&
#1720000000
b10101010 3
b111011 -
1&
#1725000000
0&
#1730000000
b111100 -
b10101011 3
1&
#1735000000
0&
#1740000000
b10101100 3
b111101 -
1&
#1745000000
0&
#1750000000
b111110 -
b10101101 3
1&
#1755000000
0&
#1760000000
b10101110 3
b111111 -
1&
#1765000000
0&
#1770000000
b1000000 -
b10101111 3
1&
#1775000000
0&
#1780000000
b10110000 3
b1000001 -
1&
#1785000000
0&
#1790000000
b1000010 -
b10110001 3
1&
#1795000000
0&
#1800000000
b10110010 3
b1000011 -
1&
#1805000000
0&
#1810000000
b1000100 -
b10110011 3
1&
#1815000000
0&
#1820000000
b10110100 3
b1000101 -
1&
#1825000000
0&
#1830000000
b1000110 -
b10110101 3
1&
#1835000000
0&
#1840000000
b10110110 3
b1000111 -
1&
#1845000000
0&
#1850000000
b1001000 -
b10110111 3
1&
#1855000000
0&
#1860000000
b10111000 3
b1001001 -
1&
#1865000000
0&
#1870000000
b1001010 -
b10111001 3
1&
#1875000000
0&
#1880000000
b10111010 3
b1001011 -
1&
#1885000000
0&
#1890000000
b1001100 -
b10111011 3
1&
#1895000000
0&
#1900000000
b10111100 3
b1001101 -
1&
#1905000000
0&
#1910000000
b1001110 -
b10111101 3
1&
#1915000000
0&
#1920000000
b10111110 3
b1001111 -
1&
#1925000000
0&
#1930000000
b1010000 -
b10111111 3
1&
#1935000000
0&
#1940000000
b11000000 3
b1010001 -
1&
#1945000000
0&
#1950000000
b1010010 -
b11000001 3
1&
#1955000000
0&
#1960000000
b11000010 3
b1010011 -
1&
#1965000000
0&
#1970000000
b1010100 -
b11000011 3
1&
#1975000000
0&
#1980000000
b11000100 3
b1010101 -
1&
#1985000000
0&
#1990000000
b1010110 -
b11000101 3
1&
#1995000000
0&
#2000000000
b11000110 3
b1010111 -
1&
#2005000000
0&
#2010000000
b1011000 -
b11000111 3
1&
#2015000000
0&
#2020000000
b11001000 3
b1011001 -
1&
#2025000000
0&
#2030000000
b1011010 -
b11001001 3
1&
#2035000000
0&
#2040000000
b11001010 3
b1011011 -
1&
#2045000000
0&
#2050000000
b1011100 -
b11001011 3
1&
#2055000000
0&
#2060000000
b11001100 3
b1011101 -
1&
#2065000000
0&
#2070000000
b1011110 -
b11001101 3
1&
#2075000000
0&
#2080000000
b11001110 3
b1011111 -
1&
#2085000000
0&
#2090000000
b1100000 -
b11001111 3
1&
#2095000000
0&
#2100000000
b11010000 3
b1100001 -
1&
#2105000000
0&
#2110000000
b1100010 -
b11010001 3
1&
#2115000000
0&
#2120000000
b11010010 3
b1100011 -
1&
#2125000000
0&
#2130000000
b1100100 -
b11010011 3
1&
#2135000000
0&
#2140000000
b11010100 3
b1100101 -
1&
#2145000000
0&
#2150000000
b1100110 -
b11010101 3
1&
#2155000000
0&
#2160000000
b11010110 3
b1100111 -
1&
#2165000000
0&
#2170000000
b1101000 -
b11010111 3
1&
#2175000000
0&
#2180000000
b11011000 3
b1101001 -
1&
#2185000000
0&
#2190000000
b1101010 -
b10 1
b0 3
1&
#2195000000
0&
#2200000000
1$
b1 3
1!
b1101011 -
1&
#2205000000
0&
#2210000000
b1101100 -
b10 3
1&
#2215000000
0&
#2220000000
b11 3
b1101101 -
1&
#2225000000
0&
#2230000000
b1101110 -
b100 3
1&
#2235000000
0&
#2240000000
b101 3
b1101111 -
1&
#2245000000
0&
#2250000000
b1110000 -
b110 3
1&
#2255000000
0&
#2260000000
b111 3
b1110001 -
1&
#2265000000
0&
#2270000000
b1110010 -
b1000 3
1&
#2275000000
0&
#2280000000
b1001 3
b1110011 -
1&
#2285000000
0&
#2290000000
b1110100 -
b1010 3
1&
#2295000000
0&
#2300000000
b1011 3
b1110101 -
1&
#2305000000
0&
#2310000000
b1110110 -
b1100 3
1&
#2315000000
0&
#2320000000
b1101 3
b1110111 -
1&
#2325000000
0&
#2330000000
b1111000 -
b1110 3
1&
#2335000000
0&
#2340000000
b1111 3
b1111001 -
1&
#2345000000
0&
#2350000000
b1111010 -
b10000 3
1&
#2355000000
0&
#2360000000
b10001 3
b1111011 -
1&
#2365000000
0&
#2370000000
b1111100 -
b10010 3
1&
#2375000000
0&
#2380000000
b10011 3
b1111101 -
1&
#2385000000
0&
#2390000000
b1111110 -
b10100 3
1&
#2395000000
0&
#2400000000
b10101 3
b1111111 -
1&
#2405000000
0&
#2410000000
b10000000 -
b10110 3
1&
#2415000000
0&
#2420000000
b10111 3
b10000001 -
1&
#2425000000
0&
#2430000000
b10000010 -
b11000 3
1&
#2435000000
0&
#2440000000
b11001 3
b10000011 -
1&
#2445000000
0&
#2450000000
b10000100 -
b11010 3
1&
#2455000000
0&
#2460000000
b11011 3
b10000101 -
1&
#2465000000
0&
#2470000000
b10000110 -
b11100 3
1&
#2475000000
0&
#2480000000
b11101 3
b10000111 -
1&
#2485000000
0&
#2490000000
b10001000 -
b11110 3
1&
#2495000000
0&
#2500000000
b11111 3
b10001001 -
1&
#2505000000
0&
#2510000000
b10001010 -
b100000 3
1&
#2515000000
0&
#2520000000
b100001 3
b10001011 -
1&
#2525000000
0&
#2530000000
b10001100 -
b100010 3
1&
#2535000000
0&
#2540000000
b100011 3
b10001101 -
1&
#2545000000
0&
#2550000000
b10001110 -
b100100 3
1&
#2555000000
0&
#2560000000
b100101 3
b10001111 -
1&
#2565000000
0&
#2570000000
b10010000 -
b100110 3
1&
#2575000000
0&
#2580000000
b100111 3
b10010001 -
1&
#2585000000
0&
#2590000000
b10010010 -
b101000 3
1&
#2595000000
0&
#2600000000
b101001 3
b10010011 -
1&
#2605000000
0&
#2610000000
b10010100 -
b101010 3
1&
#2615000000
0&
#2620000000
b101011 3
b10010101 -
1&
#2625000000
0&
#2630000000
b10010110 -
b101100 3
1&
#2635000000
0&
#2640000000
b101101 3
b10010111 -
1&
#2645000000
0&
#2650000000
b10011000 -
b101110 3
1&
#2655000000
0&
#2660000000
b101111 3
b10011001 -
1&
#2665000000
0&
#2670000000
b10011010 -
b110000 3
1&
#2675000000
0&
#2680000000
b110001 3
b10011011 -
1&
#2685000000
0&
#2690000000
b10011100 -
b110010 3
1&
#2695000000
0&
#2700000000
b110011 3
b10011101 -
1&
#2705000000
0&
#2710000000
b10011110 -
b110100 3
1&
#2715000000
0&
#2720000000
b110101 3
b10011111 -
1&
#2725000000
0&
#2730000000
b10100000 -
b110110 3
1&
#2735000000
0&
#2740000000
b110111 3
b10100001 -
1&
#2745000000
0&
#2750000000
b10100010 -
b111000 3
1&
#2755000000
0&
#2760000000
b111001 3
b10100011 -
1&
#2765000000
0&
#2770000000
b10100100 -
b111010 3
1&
#2775000000
0&
#2780000000
b111011 3
b10100101 -
1&
#2785000000
0&
#2790000000
b10100110 -
b111100 3
1&
#2795000000
0&
#2800000000
b111101 3
b10100111 -
1&
#2805000000
0&
#2810000000
b10101000 -
b111110 3
1&
#2815000000
0&
#2820000000
b111111 3
b10101001 -
1&
#2825000000
0&
#2830000000
b10101010 -
b1000000 3
1&
#2835000000
0&
#2840000000
b1000001 3
b10101011 -
1&
#2845000000
0&
#2850000000
b10101100 -
b1000010 3
1&
#2855000000
0&
#2860000000
b1000011 3
b10101101 -
1&
#2865000000
0&
#2870000000
b10101110 -
b1000100 3
1&
#2875000000
0&
#2880000000
b1000101 3
b10101111 -
1&
#2885000000
0&
#2890000000
b10110000 -
b1000110 3
1&
#2895000000
0&
#2900000000
b1000111 3
b10110001 -
1&
#2905000000
0&
#2910000000
b10110010 -
b1001000 3
1&
#2915000000
0&
#2920000000
b1001001 3
b10110011 -
1&
#2925000000
0&
#2930000000
b10110100 -
b1001010 3
1&
#2935000000
0&
#2940000000
b1001011 3
b10110101 -
1&
#2945000000
0&
#2950000000
b10110110 -
b1001100 3
1&
#2955000000
0&
#2960000000
b1001101 3
b10110111 -
1&
#2965000000
0&
#2970000000
b10111000 -
b1001110 3
1&
#2975000000
0&
#2980000000
b1001111 3
b10111001 -
1&
#2985000000
0&
#2990000000
b10111010 -
b1010000 3
1&
#2995000000
0&
#3000000000
b1010001 3
b10111011 -
1&
#3005000000
0&
#3010000000
b10111100 -
b1010010 3
1&
#3015000000
0&
#3020000000
b1010011 3
b10111101 -
1&
#3025000000
0&
#3030000000
b10111110 -
b1010100 3
1&
#3035000000
0&
#3040000000
b1010101 3
b10111111 -
1&
#3045000000
0&
#3050000000
b11000000 -
b1010110 3
1&
#3055000000
0&
#3060000000
b1010111 3
b11000001 -
1&
#3065000000
0&
#3070000000
b11000010 -
b1011000 3
1&
#3075000000
0&
#3080000000
b1011001 3
b11000011 -
1&
#3085000000
0&
#3090000000
b11000100 -
b1011010 3
1&
#3095000000
0&
#3100000000
b1011011 3
b11000101 -
1&
#3105000000
0&
#3110000000
b11000110 -
b1011100 3
1&
#3115000000
0&
#3120000000
b1011101 3
b11000111 -
1&
#3125000000
0&
#3130000000
b11001000 -
b1011110 3
1&
#3135000000
0&
#3140000000
b1011111 3
b11001001 -
1&
#3145000000
0&
#3150000000
b11001010 -
b1100000 3
1&
#3155000000
0&
#3160000000
b1100001 3
b11001011 -
1&
#3165000000
0&
#3170000000
b11001100 -
b1100010 3
1&
#3175000000
0&
#3180000000
b1100011 3
b11001101 -
1&
#3185000000
0&
#3190000000
b11001110 -
b1100100 3
1&
#3195000000
0&
#3200000000
b1100101 3
b11001111 -
1&
#3205000000
0&
#3210000000
b11010000 -
b1100110 3
1&
#3215000000
0&
#3220000000
b1100111 3
b11010001 -
1&
#3225000000
0&
#3230000000
b11010010 -
b1101000 3
1&
#3235000000
0&
#3240000000
b1101001 3
b11010011 -
1&
#3245000000
0&
#3250000000
b11010100 -
b1101010 3
1&
#3255000000
0&
#3260000000
b1101011 3
b11010101 -
1&
#3265000000
0&
#3270000000
b11010110 -
b1101100 3
1&
#3275000000
0&
#3280000000
b1101101 3
b11010111 -
1&
#3285000000
0&
#3290000000
b11011000 -
b1101110 3
1&
#3295000000
0&
#3300000000
b1101111 3
b1 .
b1 %
b1 )
b1 +
b0 -
1&
#3305000000
0&
#3310000000
b1 -
b1110000 3
1&
#3315000000
0&
#3320000000
b1110001 3
b10 -
1&
#3325000000
0&
#3330000000
b11 -
b1110010 3
1&
#3335000000
0&
#3340000000
b1110011 3
b100 -
1&
#3345000000
0&
#3350000000
b101 -
b1110100 3
1&
#3355000000
0&
#3360000000
b1110101 3
b110 -
1&
#3365000000
0&
#3370000000
b111 -
b1110110 3
1&
#3375000000
0&
#3380000000
b1110111 3
b1000 -
1&
#3385000000
0&
#3390000000
b1001 -
b1111000 3
1&
#3395000000
0&
#3400000000
b1111001 3
b1010 -
1&
#3405000000
0&
#3410000000
b1011 -
b1111010 3
1&
#3415000000
0&
#3420000000
b1111011 3
b1100 -
1&
#3425000000
0&
#3430000000
b1101 -
b1111100 3
1&
#3435000000
0&
#3440000000
b1111101 3
b1110 -
1&
#3445000000
0&
#3450000000
b1111 -
b1111110 3
1&
#3455000000
0&
#3460000000
b1111111 3
b10000 -
1&
#3465000000
0&
#3470000000
b10001 -
b10000000 3
1&
#3475000000
0&
#3480000000
b10000001 3
b10010 -
1&
#3485000000
0&
#3490000000
b10011 -
b10000010 3
1&
#3495000000
0&
#3500000000
b10000011 3
b10100 -
1&
#3505000000
0&
#3510000000
b10101 -
b10000100 3
1&
#3515000000
0&
#3520000000
b10000101 3
b10110 -
1&
#3525000000
0&
#3530000000
b10111 -
b10000110 3
1&
#3535000000
0&
#3540000000
b10000111 3
b11000 -
1&
#3545000000
0&
#3550000000
b11001 -
b10001000 3
1&
#3555000000
0&
#3560000000
b10001001 3
b11010 -
1&
#3565000000
0&
#3570000000
b11011 -
b10001010 3
1&
#3575000000
0&
#3580000000
b10001011 3
b11100 -
1&
#3585000000
0&
#3590000000
b11101 -
b10001100 3
1&
#3595000000
0&
#3600000000
b10001101 3
b11110 -
1&
#3605000000
0&
#3610000000
b11111 -
b10001110 3
1&
#3615000000
0&
#3620000000
b10001111 3
b100000 -
1&
#3625000000
0&
#3630000000
b100001 -
b10010000 3
1&
#3635000000
0&
#3640000000
b10010001 3
b100010 -
1&
#3645000000
0&
#3650000000
b100011 -
b10010010 3
1&
#3655000000
0&
#3660000000
b10010011 3
b100100 -
1&
